semver_tool/__init__.py
semver_tool/__main__.py
semver_tool/__version__.py
semver_tool-3.0.4.dist-info/LICENSE
semver_tool-3.0.4.dist-info/METADATA
semver_tool-3.0.4.dist-info/WHEEL
semver_tool-3.0.4.dist-info/entry_points.txt
semver_tool-3.0.4.dist-info/top_level.txt
semver_tool-3.0.4.dist-info/RECORD
